pyramid_mailer/__init__.py
pyramid_mailer/_compat.py
pyramid_mailer/debug.py
pyramid_mailer/exceptions.py
pyramid_mailer/interfaces.py
pyramid_mailer/mailer.py
pyramid_mailer/message.py
pyramid_mailer/testing.py
pyramid_mailer-0.15.1.dist-info/DESCRIPTION.rst
pyramid_mailer-0.15.1.dist-info/METADATA
pyramid_mailer-0.15.1.dist-info/RECORD
pyramid_mailer-0.15.1.dist-info/WHEEL
pyramid_mailer-0.15.1.dist-info/metadata.json
pyramid_mailer-0.15.1.dist-info/top_level.txt
