Metadata-Version: 1.1
Name: pyramid_mailer
Version: 0.15.1
Summary: Sendmail package for Pyramid
Home-page: http://docs.pylonsproject.org/projects/pyramid-mailer/en/latest/
Author: Dan Jacob
Author-email: danjac354@gmail.com
License: BSD
Platform: any
Classifier: Intended Audience :: Developers
Classifier: License :: OSI Approved :: BSD License
Classifier: Operating System :: OS Independent
Classifier: Topic :: Communications :: Email
Classifier: Programming Language :: Python
Classifier: Programming Language :: Python :: 2.7
Classifier: Programming Language :: Python :: 3
Classifier: Programming Language :: Python :: 3.3
Classifier: Programming Language :: Python :: 3.4
Classifier: Programming Language :: Python :: Implementation :: CPython
Classifier: Programming Language :: Python :: Implementation :: PyPy
Classifier: Framework :: Pyramid
